{
    "perros": [
        {
            "id": 1,
            "imagen": "/Perro.jpg",
            "Presentacion": "¡Guau! Mi nombre es Pandora, una perrita llena de energía y amor. Me encanta correr por el parque, jugar con mi pelota favorita y, sobre todo, hacer nuevos amigos. Tengo una habilidad especial para detectar cuándo alguien necesita una dosis extra de cariño, y siempre estoy lista para dar lametazos y recibir mimos.",
            "Nombre": "Pandora",
            "Raza": "Calle",
            "fechaNacimiento": "2023-04-15",
            "Genero": "Hembra",
            "SobreMi": "Soy muy juegetona, estoy castrada y me encanta jugar con otros perros, con los gatos no me llevo muy bien",
            "Contacto": "Gracias por cuidar de mi querida Pandora. Si la has encontrado o necesitas contactarme por cualquier motivo, por favor, no dudes en hacerlo. Pandora es una parte muy importante de nuestra familia, y estaré eternamente agradecido por tu ayuda.",
            "Telefono": 2254596659,
            "Instagram": "https://www.instagram.com/matefontaine/",
            "facebook": "",
            "Gmail": "Mateofontaine7@gmail.com",
            "iframeUrl": "https://www.google.com/maps/embed?pb=!1m18!1m12!1m3!1d3181.1059625903004!2d-56.867684123930644!3d-37.12639399506778!2m3!1f0!2f0!3f0!3m2!1i1024!2i768!4f13.1!3m3!1m2!1s0x959c9cf9d945e8e3%3A0x44952a763e2e4a56!2sSan%20Mart%C3%ADn%20268%2C%20B7167%20Ostende%2C%20Provincia%20de%20Buenos%20Aires!5e0!3m2!1sen!2sar!4v1729873612891!5m2!1sen!2sar"
        },
        {
            "id": 2,
            "imagen": "/Perro2.jpg",
            "Presentacion": "¡Guau! Mi nombre es Liza, y soy una perrita que siempre está lista para la acción y la aventura. Me encanta ser el centro de atención (¡lo admito!) y tengo una pasión por descubrir cada rincón del parque y hacerme amiga de cada humano y perrito que encuentro. En el escenario, me siento libre y feliz, porque puedo mostrarle al mundo mi verdadera esencia: una mezcla de energía, curiosidad y un corazón gigante lleno de amor.Tengo un olfato especial para reconocer cuándo alguien necesita una buena dosis de compañía y cariño. Si estás triste, ahí estaré, lista para darte un buen lametazo y poner una sonrisa en tu cara. ¡Así que prepárense para una noche llena de diversión y muchos, muchos ladridos!",
            "Nombre": "Liza",
            "Raza": "Calle",
            "fechaNacimiento": "2017-04-21",
            "Genero": "Hembra",
            "SobreMi": "¡Hola! Soy Liza, una perrita tranquila y muy juguetona. Me llevo bien con todos los animales (aunque con los gatos no tanto) y con los nenes me dejo hacer de todo. ¡Listos para jugar y compartir mucho cariño!",
            "Contacto": "Gracias por cuidar a mi querida Liza. Si la has encontrado o necesitas contactarme por cualquier motivo, no dudes en hacerlo. Liza es una parte muy importante de nuestra familia, y siempre estaré agradecido por tu ayuda.",
            "Telefono": 1135602727,
            "Instagram": "",
            "facebook": "",
            "Gmail": "",
            "iframeUrl":"https://www.google.com/maps/embed?pb=!1m14!1m12!1m3!1d3291.1294289837065!2d-58.62206244486457!3d-34.42346735769389!2m3!1f0!2f0!3f0!3m2!1i1024!2i768!4f13.1!5e0!3m2!1sen!2sar!4v1729910984889!5m2!1sen!2sar"
        },
        {
            "id": 3,
            "imagen": "/Perro3.jpeg",
            "Presentacion": "¡Guau! Mi nombre es Olivia, y soy una perrita que siempre está lista para la acción y la aventura. Me encanta ser el centro de atención (¡lo admito!) y tengo una pasión por descubrir cada rincón del parque y hacerme amiga de cada humano y perrito que encuentro. En el escenario, me siento libre y feliz, porque puedo mostrarle al mundo mi verdadera esencia: una mezcla de energía, curiosidad y un corazón gigante lleno de amor.Tengo un olfato especial para reconocer cuándo alguien necesita una buena dosis de compañía y cariño. Si estás triste, ahí estaré, lista para darte un buen lametazo y poner una sonrisa en tu cara. ¡Así que prepárense para una noche llena de diversión y muchos, muchos ladridos!",
            "Nombre": "Olivia",
            "Raza": "Yorkshire",
            "fechaNacimiento": "2012-03-02",
            "Genero": "Hembra",
            "SobreMi": "¡Hola! Soy Olivia, una perrita tranquila y muy juguetona. Me llevo bien con todos los animales (aunque con los gatos no tanto) y con los nenes me dejo hacer de todo. ¡Listos para jugar y compartir mucho cariño!",
            "Contacto": "Gracias por cuidar a mi querida Oli. Si la has encontrado o necesitas contactarme por cualquier motivo, no dudes en hacerlo. Oli es una parte muy importante de nuestra familia, y siempre estaré agradecido por tu ayuda.",
            "Telefono": 2267444899,
            "Instagram": "",
            "facebook": "",
            "Gmail": "",
            "iframeUrl":"https://www.google.com/maps/embed?pb=!1m18!1m12!1m3!1d3180.99835776509!2d-56.87605362393061!3d-37.128954095211924!2m3!1f0!2f0!3f0!3m2!1i1024!2i768!4f13.1!3m3!1m2!1s0x959c9cfef9b4d5e5%3A0x9996c3202b3bc30b!2sDefensa%20699%2C%20B7167%20Ostende%2C%20Provincia%20de%20Buenos%20Aires!5e0!3m2!1ses!2sar!4v1730386834410!5m2!1ses!2sar"
        },
        {
            "id": 4,
            "imagen": "/Perro4.jpg",
            "Presentacion": "Soy el más malcriado de la manada,  el único que viaja a todos lados, no solo a pasear...me voy de vacaciones! Duermo en carpa, dormis y hostels, me llevan a trabajar a la vete todos los días y duermo en la cama con mi hermano humano y mis mamás. Mi momento preferido es cuando vamos toda la manada humana y perruna al bosque o la playa ❤️",
            "Nombre": "NeLsOn",
            "Raza": "mezcla de varias",
            "fechaNacimiento": "2015-01-01",
            "Genero": "Macho castrado",
            "SobreMi": "Soy muy amigable con otros perros y gatos 🥰",
            "Contacto": "Reteneme hasta q me busque mi mamá porfa o llévame a la vete en2patas.",
            "Telefono": 2267473665,
            "Instagram": "https://www.instagram.com/Celes__martin/",
            "facebook": "",
            "Gmail": "celmartin87@gmail.com",
            "iframeUrl":"https://www.google.com/maps/embed?pb=!1m18!1m12!1m3!1d3181.9028878508643!2d-56.874455023408615!3d-37.107429094002526!2m3!1f0!2f0!3f0!3m2!1i1024!2i768!4f13.1!3m3!1m2!1s0x959c9cd936279173%3A0xaa5795cd3a960af9!2sDel%20Caz%C3%B3n%201525%2C%20B7167%20Pinamar%2C%20Provincia%20de%20Buenos%20Aires!5e0!3m2!1sen!2sar!4v1733613090980!5m2!1sen!2sar"
        },
        {
            "id": 5,
            "imagen": "/Perro5.jpeg",
            "Presentacion": "Soy Julián pero me dicen Pei, soy juguetón, obediente y muy familiero. Por eso si me encontras llama rápido a mi familia porque mis dueños Ema, Tomás y Josefina me están esperando",
            "Nombre": "Julián",
            "Raza": "Caniche mini toy",
            "fechaNacimiento": "2023-06-15",
            "Genero": "macho",
            "SobreMi": "Llegué a mi familia en un momento muy especial y Josefina que hoy tiene 9 años siempre me dice que le cambie la vida.",
            "Contacto": "Ema Cincunegui(+54 9 2267 47‑5099), Sebastian Cincunegui(+54 9 2267 40-3974) y Lilen Grispino(+54 9 2267 40-1049).",
            "Telefono": 2267475099,
            "Instagram": "https://www.instagram.com/emacincunegui_/",
            "facebook": "",
            "Gmail": "sebastiancincunegui@gmail.com",
            "iframeUrl":"https://www.google.com/maps/embed?pb=!1m18!1m12!1m3!1d3181.4395471932417!2d-56.87524382340815!3d-37.11845649462243!2m3!1f0!2f0!3f0!3m2!1i1024!2i768!4f13.1!3m3!1m2!1s0x959c9ce3d4dbea63%3A0x14f1f27da6001fc!2sDe%20las%20Ondinas%201317%2C%20B7167%20Pinamar%2C%20Provincia%20de%20Buenos%20Aires!5e0!3m2!1sen!2sar!4v1733750641200!5m2!1sen!2sar"
        },
        {
            "id": 6,
            "imagen": "/Perro6.jpeg",
            "Presentacion": "Marta es una perra cariñosa y energética que siempre está lista para jugar y hacer sonreír. Le encanta correr por el parque y acurrucarse en el sofá. Con su lealtad incondicional y su alegría, es una parte imprescindible de la familia.",
            "Nombre": "Marta",
            "Raza": "De la calle",
            "fechaNacimiento": "2014-01-01",
            "Genero": "hembra",
            "SobreMi": "",
            "Contacto": "Gracias por cuidar de mi querida Marta. Si la has encontrado o necesitas contactarme por cualquier motivo, por favor, no dudes en hacerlo. Marta es una parte muy importante de nuestra familia, y estaré eternamente agradecido por tu ayuda.",
            "Telefono": 2254530092,
            "Instagram": "https://www.instagram.com/carlospetraru/",
            "facebook": "",
            "Gmail": "carlospetraru@hotmail.com ",
            "iframeUrl":"https://www.google.com/maps/embed?pb=!1m18!1m12!1m3!1d3181.540859585097!2d-56.88236241092229!3d-37.11604552268807!2m3!1f0!2f0!3f0!3m2!1i1024!2i768!4f13.1!3m3!1m2!1s0x959c9d1fc780dc1f%3A0x6b8142564f214c29!2sDe%20los%20Titanes%201529%2C%20B7167%20Pinamar%2C%20Provincia%20de%20Buenos%20Aires!5e0!3m2!1sen!2sar!4v1733763375612!5m2!1sen!2sar"
        },
        {
            "id": 7,
            "imagen": "/Perro7.png",
            "Presentacion": "Hola! Soy Max Yañez.",
            "Nombre": "Max",
            "Raza": "Teckel",
            "fechaNacimiento": "Naci el 9/11/24",
            "Genero": "Macho",
            "SobreMi": "Amo a mi familia!",
            "Contacto": "Gabriela o Nicolás.",
            "Telefono": 2254526208,
            "Instagram": "https://www.instagram.com/chuikchuikok/",
            "facebook": "",
            "Gmail": "chuikchuik.pinamar@gmail.com",
            "iframeUrl":"https://www.google.com/maps/embed?pb=!1m18!1m12!1m3!1d3181.614470311464!2d-56.86653252340831!3d-37.11429369438846!2m3!1f0!2f0!3f0!3m2!1i1024!2i768!4f13.1!3m3!1m2!1s0x959c9ce8ba7c110f%3A0xdfccba191d72b43a!2sJonas%20640%2C%20B7167%20Pinamar%2C%20Provincia%20de%20Buenos%20Aires!5e0!3m2!1sen!2sar!4v1733791206452!5m2!1sen!2sar"
        },
        {
            "id": 8,
            "imagen": "/Perro8.jpeg",
            "Presentacion": "Hola, soy coco!.",
            "Nombre": "Coco Lambusta",
            "Raza": "Golden Retriever",
            "fechaNacimiento": "2024-08-09",
            "Genero": "Macho",
            "SobreMi": "Me gusta jugar y romper cosas, pero soy bueno y sano.",
            "Contacto": "Octavio Lambusta.",
            "Telefono": 2254612660,
            "Instagram": "https://www.instagram.com/Otilambusta/",
            "facebook": "",
            "Gmail": "Lambustavio@gmail.com",
            "iframeUrl":"https://www.google.com/maps/embed?pb=!1m18!1m12!1m3!1d3181.6433368102826!2d-56.878262323408315!3d-37.11360669434966!2m3!1f0!2f0!3f0!3m2!1i1024!2i768!4f13.1!3m3!1m2!1s0x959c9d200b1abe8b%3A0xa130eed1e1dd1f9f!2sDe%20las%20Nayades%2C%20B7167%20Pinamar%2C%20Provincia%20de%20Buenos%20Aires!5e0!3m2!1sen!2sar!4v1733791502885!5m2!1sen!2sar"
        },
        {
            "id": 9,
            "imagen": "/Perro9.jpeg",
            "Presentacion": "Mi nombre es Derek, estoy castrado, soy juguetón con perros y humanos.",
            "Nombre": "Derek",
            "Raza": "Weimaraner",
            "fechaNacimiento": "2018-01-01",
            "Genero": "Macho",
            "SobreMi": "Alejandro Bienaimé.",
            "Contacto": "Alejandro Bienaimé ",
            "Telefono": 1123012001,
            "Instagram": "https://www.instagram.com/alebien/",
            "facebook": "",
            "Gmail": "alebien@gmail.com",
            "iframeUrl":"https://www.google.com/maps/embed?pb=!1m18!1m12!1m3!1d3182.4445419628246!2d-56.84899202340915!3d-37.094534293277775!2m3!1f0!2f0!3f0!3m2!1i1024!2i768!4f13.1!3m3!1m2!1s0x959c9cb09849e269%3A0xd476ccca1d14faa!2sDe%20los%20Alamos%20685%2C%20B7167%20Pinamar%2C%20Provincia%20de%20Buenos%20Aires!5e0!3m2!1sen!2sar!4v1733855315468!5m2!1sen!2sar"
        },
        {
            "id": 10,
            "imagen": "/Perro10.jpeg",
            "Presentacion": "Soy súper cariñosa y amigable con perros y humanos.",
            "Nombre": "Princesa",
            "Raza": "Yorky",
            "fechaNacimiento": "2023-04-21",
            "Genero": "Hembra",
            "SobreMi": "Soy hermosa y mimada por mi familia Si llego a perderme no sabría vivir sin ellos.",
            "Contacto": "Celeste",
            "Telefono": 2254524498,
            "Instagram": "https://www.instagram.com/chelealonso/",
            "facebook": "",
            "Gmail": "celeste.alonso1980@gmail.com",
            "iframeUrl":"https://www.google.com/maps/embed?pb=!1m18!1m12!1m3!1d3180.4125501643125!2d-56.88231702340705!3d-37.14288879599665!2m3!1f0!2f0!3f0!3m2!1i1024!2i768!4f13.1!3m3!1m2!1s0x959c9dad963deb75%3A0x98b40a6a5b2f7176!2sCap.%20de%20Marina%20E.%20G.%20Parquer%20372%2C%20B7167%20Valeria%20del%20Mar%2C%20Provincia%20de%20Buenos%20Aires!5e0!3m2!1sen!2sar!4v1733856127220!5m2!1sen!2sar"
        },
        {
            "id": 11,
            "imagen": "",
            "Presentacion": "Hola soy Pintu, vivo en Pinamar, me encanta jugar con piedras y dormir al sol.",
            "Nombre": "Pintu",
            "Raza": "Boxer",
            "fechaNacimiento": "2023-04-21",
            "Genero": "Macho",
            "SobreMi": "Soy Lucia, madre de Pintu, lo más divertido y alegre es estar con el, ya que vive pegado al culo mio.",
            "Contacto": "Celeste",
            "Telefono": 2267438966,
            "Instagram": "https://www.instagram.com/Migliaccio_lucia/",
            "facebook": "",
            "Gmail": "Lucmigliaccio@gmail.com",
            "iframeUrl":"https://www.google.com/maps/embed?pb=!1m18!1m12!1m3!1d3180.4125501643125!2d-56.88231702340705!3d-37.14288879599665!2m3!1f0!2f0!3f0!3m2!1i1024!2i768!4f13.1!3m3!1m2!1s0x959c9dad963deb75%3A0x98b40a6a5b2f7176!2sCap.%20de%20Marina%20E.%20G.%20Parquer%20372%2C%20B7167%20Valeria%20del%20Mar%2C%20Provincia%20de%20Buenos%20Aires!5e0!3m2!1sen!2sar!4v1733856127220!5m2!1sen!2sar"
        },
        {
            "id": 12,
            "imagen": "/Perro12.jpg",
            "Presentacion": "Soy juguetona.",
            "Nombre": "Pipa",
            "Raza": "Jack Rusell Terrier",
            "fechaNacimiento": "2024-08-18",
            "Genero": "Hembra",
            "SobreMi": "Manchas blancas, marrones y bigotes negros.",
            "Contacto": "Alejandra",
            "Telefono": 2267639612,
            "Instagram": "",
            "facebook": "",
            "Gmail": "alericcicaro@gmail.com",
            "iframeUrl":"https://www.google.com/maps/embed?pb=!1m18!1m12!1m3!1d3180.52962414889!2d-56.911380823299154!3d-37.14010429584003!2m3!1f0!2f0!3f0!3m2!1i1024!2i768!4f13.1!3m3!1m2!1s0x959c9de87b2dd491%3A0xec11ae89a5df2c1f!2sSuboficial%20J.%20N.%20Aguila%20749%2C%20B7167%20Valeria%20del%20Mar%2C%20Provincia%20de%20Buenos%20Aires!5e0!3m2!1sen!2sar!4v1734021287202!5m2!1sen!2sar"
        },
        {
            "id": 13,
            "imagen": "/Perro13.jpeg",
            "Presentacion": "🐶",
            "Nombre": "Arya",
            "Raza": "Golden Retriever",
            "fechaNacimiento": "2022-01-01",
            "Genero": "Hembra",
            "SobreMi": "Soy súper inquieta y tengo energía de sobra. A veces algo complicada con los perros en general después de una mala experiencia, pero súper cariñosa.",
            "Contacto": "Alejandro",
            "Telefono": 1140827668,
            "Instagram": "https://www.instagram.com/Alejandroepiccolo/",
            "facebook": "",
            "Gmail": "Piccoloale85@gmail.com",
            "iframeUrl":"https://www.google.com/maps/embed?pb=!1m18!1m12!1m3!1d26243.217375860473!2d-58.436938447800266!3d-34.69503488193759!2m3!1f0!2f0!3f0!3m2!1i1024!2i768!4f13.1!3m3!1m2!1s0x95bcccfbdfe9ce15%3A0xf96ae66cb468bd9f!2sLan%C3%BAs%20Oeste%2C%20B1824%20Lan%C3%BAs%2C%20Buenos%20Aires%20Province!5e0!3m2!1sen!2sar!4v1733951138492!5m2!1sen!2sar"
        },
        {
            "id": 14,
            "imagen": "/Perro14.jpg",
            "Presentacion": "Leoncita tiene apenas 2 meses. La dejaron abandonada en la puerta de la casa de una persona, que fue la que me la dio en adopción. Es muy juguetona, inteligente, dulce e inquieta. El 13/12 le dieron su primer vacuna. Goza de buena salud.",
            "Nombre": "Leona",
            "Raza": "Indefinida",
            "fechaNacimiento": "2024-10-01",
            "Genero": "Hembra",
            "SobreMi": "Mi nombre es Sofía Lezcano. Tengo 31 años y soy Psicopedagoga. Vivo con en ella en un duplex en Mar de Ostende (Prov. Bs.As)",
            "Contacto": "Si allí no me encuentran, estaré en Av. Tridente 969. (2267-666423)",
            "Telefono": 2254457574 ,
            "Instagram": "https://www.instagram.com/Lic.sofialezcano/",
            "facebook": "",
            "Gmail": "Lic.psp.sofialezcano@gmail.com",
            "iframeUrl":"https://www.google.com/maps/embed?pb=!1m18!1m12!1m3!1d3180.800818438305!2d-56.87913592196071!3d-37.13365349547942!2m3!1f0!2f0!3f0!3m2!1i1024!2i768!4f13.1!3m3!1m2!1s0x959c9daaa92395a7%3A0x147969a33a7ae2e!2sAv.%20Robette%20743%2C%20B7167%20Ostende%2C%20Provincia%20de%20Buenos%20Aires!5e0!3m2!1sen!2sar!4v1734187697570!5m2!1sen!2sar"
        },
        {
            "id": 15,
            "imagen": "/Perro15.jpeg",
            "Presentacion": "Hola! Soy coki una perrita de pinamar, medio timida pero muy buena.",
            "Nombre": "Coki",
            "Raza": "De la calle",
            "fechaNacimiento": "2018-06-01",
            "Genero": "Hembra",
            "SobreMi": "Soy una perrita castrada con mis vacunas al dia. Siempre estoy por mi casa o por el balneario cocodrilo donde trabajan mis papas. Soy medio asustadiza cuando no conozco a la gente pero soy buenita",
            "Contacto": "Gabriel Luis Enrique Martinez",
            "Telefono": 2267530889,
            "Instagram": "https://www.instagram.com/malemartinezvolpe/",
            "facebook": "",
            "Gmail": "malenamartinezvolpe@gmail.com",
            "iframeUrl":"https://www.google.com/maps/embed?pb=!1m18!1m12!1m3!1d3182.5356027255375!2d-56.84859442330098!3d-37.09236609315623!2m3!1f0!2f0!3f0!3m2!1i1024!2i768!4f13.1!3m3!1m2!1s0x959c9cbaab48ba6b%3A0xb74beb49c1d4a134!2sDe%20las%20Garzas%2C%20B7167%20Pinamar%2C%20Provincia%20de%20Buenos%20Aires!5e0!3m2!1sen!2sar!4v1734306880763!5m2!1sen!2sar"
        },
        {
            "id": 16,
            "imagen": "/Perro16.jpg",
            "Presentacion": "Hola!! soy Thor, tengo tres años y tengo dos hermanas gatunas más grandes. Me llevo bien con todos, aunque a veces me molesta un poco que me olfateen mucho. No me gusta pelear, asique cuando un perro me viene a ladrar, lo ignoro y sigo caminando. Me gusta jugar con pelotas, palitos, piñas y todo lo que pueda masticarse. Y cuando tengo el pelo largo, la gente me confunde con un oso! Soy un perro super dulce, y me gusta mucho que me hagan mimos. ",
            "Nombre": "Thor ⚡",
            "Raza": "Cruza",
            "fechaNacimiento": "2021-05-13",
            "Genero": "Macho",
            "SobreMi": "No estoy castrado aún, soy algo timido, y con los gatos me llevo bien.",
            "Contacto": "Mi nombre es Emilia, y soy la mamá de Thor. Thor no está acostumbrado a estar suelto, por lo tanto si lo encontraste, te pido por favor que lo retengas y me avises. Él es mi compañero, y una parte muy importante de mi familia. Te agradezco de ante mano por cuidarlo 💕",
            "Telefono": 111528895947,
            "Instagram": "https://www.instagram.com/m.emiliaf/",
            "facebook": "https://www.facebook.com/m.emilia.farias",
            "Gmail": "memiliaf9@gmail.com",
            "iframeUrl":"https://www.google.com/maps/embed?pb=!1m18!1m12!1m3!1d3181.8232862154614!2d-56.87367202330033!3d-37.10932379410907!2m3!1f0!2f0!3f0!3m2!1i1024!2i768!4f13.1!3m3!1m2!1s0x959c9cde9a95ff31%3A0xa34acf24c757e90b!2sAv.%20Constituci%C3%B3n%201345%2C%20B7167%20Pinamar%2C%20Provincia%20de%20Buenos%20Aires!5e0!3m2!1sen!2sar!4v1734366461543!5m2!1sen!2sar"
        },
        {
            "id": 17,
            "imagen": "/Perro17.jpeg",
            "Presentacion": "Mansita",
            "Nombre": "Shiva",
            "Raza": "Pit",
            "fechaNacimiento": "2023-02-10",
            "Genero": "Hembra",
            "SobreMi": ".",
            "Contacto": "Sonia",
            "Telefono": 1157037035,
            "Instagram": "https://www.instagram.com/_sonicuixx_",
            "facebook": "",
            "Gmail": "memiliaf9@gmail.com",
            "iframeUrl":"https://www.google.com/maps/embed?pb=!1m18!1m12!1m3!1d3186.262361120698!2d-56.80792832345264!3d-37.00353687218976!2m3!1f0!2f0!3f0!3m2!1i1024!2i768!4f13.1!3m3!1m2!1s0x959c84494f8badc5%3A0x5f758c8af2eff74b!2sCosta%20Esmeralda!5e0!3m2!1sen!2sar!4v1735677045265!5m2!1sen!2sar"
        },
        {
            "id": 18,
            "imagen": "/Perro18.jpeg",
            "Presentacion": "Soy el negro mas lindo de la casa y un eterno cachorro!!! soy muy mimoso y compañero! duermo en el cuarto de mi hermana de dos patas !!",
            "Nombre": "BUZZ",
            "Raza": "Labrador",
            "fechaNacimiento": "2013-05-31",
            "Genero": "Masculino",
            "SobreMi": "Soy un labrador negro de 11 años . Me cuesta sociabilizar con otros perros . No me den de comer huesos y me encanta meterme al agua !!",
            "Contacto": "si me encontras es xque estoy perdido x favor contactate urgente con mis papas que son Veronica o Carlos. Gracias (+5492215774182)",
            "Telefono": 2214091751,
            "Instagram": "https://www.instagram.com/veroilazzaro ",
            "facebook": "",
            "Gmail": "verotatilazzaro@gmail.com",
            "iframeUrl":"https://www.google.com/maps/embed?pb=!1m18!1m12!1m3!1d3272.6431350791863!2d-58.06497532338759!3d-34.890306572691586!2m3!1f0!2f0!3f0!3m2!1i1024!2i768!4f13.1!3m3!1m2!1s0x95a2dc2fa15faec1%3A0xe5573f46206219d3!2sC.%2031%20Bis%20659%2C%20B1902%20City%20Bell%2C%20Provincia%20de%20Buenos%20Aires!5e0!3m2!1sen!2sar!4v1735938656262!5m2!1sen!2sar"
        },
        {
            "id": 19,
            "imagen": "/Perro19.jpg",
            "Presentacion": "Hola soy 🫒 oliva, por favor llamar a mis dueños",
            "Nombre": "Oliva",
            "Raza": "Bulldog francés",
            "fechaNacimiento": "2024-12-05",
            "Genero": "femenino",
            "SobreMi": "",
            "Contacto": "",
            "Telefono": 2254446678,
            "Instagram": "",
            "facebook": "",
            "Gmail": "Ávila.lautaro@icloud.com",
            "iframeUrl":"https://www.google.com/maps/embed?pb=!1m18!1m12!1m3!1d3182.0252475206594!2d-56.8642855233005!3d-37.10451649383895!2m3!1f0!2f0!3f0!3m2!1i1024!2i768!4f13.1!3m3!1m2!1s0x959c9cc47f18744b%3A0x4b293f0f0e8df413!2sDel%20Cornalito%201256%2C%20B7167%20Pinamar%2C%20Provincia%20de%20Buenos%20Aires!5e0!3m2!1sen!2sar!4v1736018708273!5m2!1sen!2sar"
        }

    ]
}